{
    "esifdipj1409":  "SPED / layouts DIPJ",
    "esrsc15":  "Relatorios e obrigacoes (matriz estadual)",
    "esrms06":  "Relatorios e obrigacoes (matriz estadual)",
    "esr12":  "Relatorios e obrigacoes (matriz estadual)",
    "esc02":  "Nucleo escrituracao (esc)",
    "esr21":  "Relatorios e obrigacoes (matriz estadual)",
    "esreroissportovelho":  "Relatorios e obrigacoes (matriz estadual)",
    "esapuracao06":  "Apuracao de impostos",
    "esc09":  "Nucleo escrituracao (esc)",
    "esm_drcst":  "Layouts / ajustes (prefixo esm_)",
    "esr75":  "Relatorios e obrigacoes (matriz estadual)",
    "esapuracao09":  "Apuracao de impostos",
    "esrmg05":  "Relatorios e obrigacoes (matriz estadual)",
    "esrba07":  "Relatorios e obrigacoes (matriz estadual)",
    "esisitecte02":  "Cadastros site / portal / CTe",
    "esr103":  "Relatorios e obrigacoes (matriz estadual)",
    "esutilalteracao04":  "Utilitarios e alteracoes",
    "esr72":  "Relatorios e obrigacoes (matriz estadual)",
    "esr19":  "Relatorios e obrigacoes (matriz estadual)",
    "esrpe02":  "Relatorios e obrigacoes (matriz estadual)",
    "esapuracaosimplesnacional03":  "Apuracao de impostos",
    "esifdipj1403":  "SPED / layouts DIPJ",
    "esapuracao13":  "Apuracao de impostos",
    "esrsp06":  "Relatorios e obrigacoes (matriz estadual)",
    "esr91":  "Relatorios e obrigacoes (matriz estadual)",
    "esm53":  "Movimento e parametros (esm)",
    "esrpi01":  "Relatorios e obrigacoes (matriz estadual)",
    "esm42":  "Movimento e parametros (esm)",
    "esrsc05":  "Relatorios e obrigacoes (matriz estadual)",
    "esm71":  "Movimento e parametros (esm)",
    "esr82":  "Relatorios e obrigacoes (matriz estadual)",
    "esiwebserviceportalfederal02":  "Integracoes / canais digitais",
    "esr40":  "Relatorios e obrigacoes (matriz estadual)",
    "esutilalteracao05":  "Utilitarios e alteracoes",
    "esr13":  "Relatorios e obrigacoes (matriz estadual)",
    "esc03":  "Nucleo escrituracao (esc)",
    "esr26":  "Relatorios e obrigacoes (matriz estadual)",
    "esr31":  "Relatorios e obrigacoes (matriz estadual)",
    "esapuracao07":  "Apuracao de impostos",
    "esm67":  "Movimento e parametros (esm)",
    "esrrs09":  "Relatorios e obrigacoes (matriz estadual)",
    "esutilalteracao02":  "Utilitarios e alteracoes",
    "esrpr03":  "Relatorios e obrigacoes (matriz estadual)",
    "esrro04":  "Relatorios e obrigacoes (matriz estadual)",
    "esobj":  "Nucleo escrituracao (esc)",
    "esm06":  "Movimento e parametros (esm)",
    "esr70":  "Relatorios e obrigacoes (matriz estadual)",
    "esrgo13":  "Relatorios e obrigacoes (matriz estadual)",
    "esm85":  "Movimento e parametros (esm)",
    "esisitesefazrs01":  "Sefaz e sites estaduais",
    "esf01":  "Movimento fiscal (esf)",
    "esrrs18":  "Relatorios e obrigacoes (matriz estadual)",
    "esm58":  "Movimento e parametros (esm)",
    "esutilalteracao06":  "Utilitarios e alteracoes",
    "esisitesefazrs04":  "Sefaz e sites estaduais",
    "esrce04":  "Relatorios e obrigacoes (matriz estadual)",
    "esr90":  "Relatorios e obrigacoes (matriz estadual)",
    "esrac03":  "Relatorios e obrigacoes (matriz estadual)",
    "esm55":  "Movimento e parametros (esm)",
    "esr41":  "Relatorios e obrigacoes (matriz estadual)",
    "esm44":  "Movimento e parametros (esm)",
    "esm77":  "Movimento e parametros (esm)",
    "esapuracao11":  "Apuracao de impostos",
    "esm66":  "Movimento e parametros (esm)",
    "esrmt03":  "Relatorios e obrigacoes (matriz estadual)",
    "esutil02":  "Utilitarios e alteracoes",
    "esrms01":  "Relatorios e obrigacoes (matriz estadual)",
    "esc12":  "Nucleo escrituracao (esc)",
    "esram02":  "Relatorios e obrigacoes (matriz estadual)",
    "esm61":  "Movimento e parametros (esm)",
    "esr100":  "Relatorios e obrigacoes (matriz estadual)",
    "esr37":  "Relatorios e obrigacoes (matriz estadual)",
    "esrto01":  "Relatorios e obrigacoes (matriz estadual)",
    "esres02":  "Relatorios e obrigacoes (matriz estadual)",
    "esrrj07":  "Relatorios e obrigacoes (matriz estadual)",
    "esm08":  "Movimento e parametros (esm)",
    "esrgo14":  "Relatorios e obrigacoes (matriz estadual)",
    "esr69":  "Relatorios e obrigacoes (matriz estadual)",
    "esifdipj1205":  "SPED / layouts DIPJ",
    "esr87":  "Relatorios e obrigacoes (matriz estadual)",
    "esrap01":  "Relatorios e obrigacoes (matriz estadual)",
    "esr04":  "Relatorios e obrigacoes (matriz estadual)",
    "esipainelapi":  "Integracoes / painel e analytics",
    "esnfeatendimento":  "Atendimento NF-e",
    "esrrs17":  "Relatorios e obrigacoes (matriz estadual)",
    "esrse01":  "Relatorios e obrigacoes (matriz estadual)",
    "esrsp02":  "Relatorios e obrigacoes (matriz estadual)",
    "esf19":  "Movimento fiscal (esf)",
    "esifixoempresaspedfiscal":  "SPED / layouts fixos e documentos eletronicos",
    "esrba02":  "Relatorios e obrigacoes (matriz estadual)",
    "esrsp17":  "Relatorios e obrigacoes (matriz estadual)",
    "esr88":  "Relatorios e obrigacoes (matriz estadual)",
    "esichromium":  "Integracoes / canais digitais",
    "esutil01":  "Utilitarios e alteracoes",
    "esm_cfe":  "Layouts / ajustes (prefixo esm_)",
    "esrrs06":  "Relatorios e obrigacoes (matriz estadual)",
    "esr_memoria_calculo_entrada":  "API contador / DEFIS / PGDAS / memorias",
    "esc13":  "Nucleo escrituracao (esc)",
    "esisitecadastros":  "Cadastros site / portal / CTe",
    "esr45":  "Relatorios e obrigacoes (matriz estadual)",
    "esrma01":  "Relatorios e obrigacoes (matriz estadual)",
    "esr54":  "Relatorios e obrigacoes (matriz estadual)",
    "esr67":  "Relatorios e obrigacoes (matriz estadual)",
    "esobjetosglobais":  "Nucleo escrituracao (esc)",
    "esm39":  "Movimento e parametros (esm)",
    "esifdipj1304":  "SPED / layouts DIPJ",
    "esm28":  "Movimento e parametros (esm)",
    "esifixobilhetepassagem02":  "SPED / layouts fixos e documentos eletronicos",
    "esifixosintegra01":  "SPED / layouts fixos e documentos eletronicos",
    "esr03":  "Relatorios e obrigacoes (matriz estadual)",
    "esrsc14":  "Relatorios e obrigacoes (matriz estadual)",
    "esr79":  "Relatorios e obrigacoes (matriz estadual)",
    "esr_memoria_calculo_resumo":  "API contador / DEFIS / PGDAS / memorias",
    "esr86":  "Relatorios e obrigacoes (matriz estadual)",
    "esrrs11":  "Relatorios e obrigacoes (matriz estadual)",
    "esapuracao15":  "Apuracao de impostos",
    "esr05":  "Relatorios e obrigacoes (matriz estadual)",
    "esr101":  "Relatorios e obrigacoes (matriz estadual)",
    "esrrs08":  "Relatorios e obrigacoes (matriz estadual)",
    "esutilalteracao07":  "Utilitarios e alteracoes",
    "esm40":  "Movimento e parametros (esm)",
    "esram01":  "Relatorios e obrigacoes (matriz estadual)",
    "esf25":  "Movimento fiscal (esf)",
    "esrba01":  "Relatorios e obrigacoes (matriz estadual)",
    "esrrs04":  "Relatorios e obrigacoes (matriz estadual)",
    "esobj04":  "Nucleo escrituracao (esc)",
    "esapuracao01":  "Apuracao de impostos",
    "esm_obs_info_comp_01":  "Layouts / ajustes (prefixo esm_)",
    "esc26":  "Nucleo escrituracao (esc)",
    "esm15":  "Movimento e parametros (esm)",
    "esifixonfsenacional02":  "SPED / layouts fixos e documentos eletronicos",
    "esrsc13":  "Relatorios e obrigacoes (matriz estadual)",
    "esm37":  "Movimento e parametros (esm)",
    "esm83":  "Movimento e parametros (esm)",
    "esm26":  "Movimento e parametros (esm)",
    "esrpr13":  "Relatorios e obrigacoes (matriz estadual)",
    "esf07":  "Movimento fiscal (esf)",
    "esrsc02":  "Relatorios e obrigacoes (matriz estadual)",
    "esres03":  "Relatorios e obrigacoes (matriz estadual)",
    "esr77":  "Relatorios e obrigacoes (matriz estadual)",
    "esifdipj1305":  "SPED / layouts DIPJ",
    "esm29":  "Movimento e parametros (esm)",
    "esrrj04":  "Relatorios e obrigacoes (matriz estadual)",
    "esifixonfag":  "SPED / layouts fixos e documentos eletronicos",
    "esram03":  "Relatorios e obrigacoes (matriz estadual)",
    "esimodeloutilitario":  "SPED / modelo utilitario",
    "esapuracaoconsulta":  "Apuracao de impostos",
    "esrdf02":  "Relatorios e obrigacoes (matriz estadual)",
    "esr20":  "Relatorios e obrigacoes (matriz estadual)",
    "esrro03":  "Relatorios e obrigacoes (matriz estadual)",
    "esapuracao_drcst_pr":  "Apuracao de impostos",
    "esrsc08":  "Relatorios e obrigacoes (matriz estadual)",
    "esiwebserviceportalfederal":  "Integracoes / canais digitais",
    "esral01":  "Relatorios e obrigacoes (matriz estadual)",
    "esisitesefazsc02":  "Sefaz e sites estaduais",
    "esrgdemonstrativosimpostos03":  "Relatorios e obrigacoes (matriz estadual)",
    "esrrs07":  "Relatorios e obrigacoes (matriz estadual)",
    "esidigitalbank":  "Integracoes / canais digitais",
    "esr18":  "Relatorios e obrigacoes (matriz estadual)",
    "esapuracao_drcst":  "Apuracao de impostos",
    "esm10":  "Movimento e parametros (esm)",
    "esf09":  "Movimento fiscal (esf)",
    "esapuracaosimplesnacional01":  "Apuracao de impostos",
    "esm27":  "Movimento e parametros (esm)",
    "esifdipj1405":  "SPED / layouts DIPJ",
    "esf04":  "Movimento fiscal (esf)",
    "esrsp04":  "Relatorios e obrigacoes (matriz estadual)",
    "esr93":  "Relatorios e obrigacoes (matriz estadual)",
    "esrms02":  "Relatorios e obrigacoes (matriz estadual)",
    "esrsc06":  "Relatorios e obrigacoes (matriz estadual)",
    "escrita":  "Nucleo escrituracao (esc)",
    "esrrs01":  "Relatorios e obrigacoes (matriz estadual)",
    "esc17":  "Nucleo escrituracao (esc)",
    "esc05":  "Nucleo escrituracao (esc)",
    "esr27":  "Relatorios e obrigacoes (matriz estadual)",
    "esrsc10":  "Relatorios e obrigacoes (matriz estadual)",
    "esapuracao05":  "Apuracao de impostos",
    "esrsp10":  "Relatorios e obrigacoes (matriz estadual)",
    "esrro02":  "Relatorios e obrigacoes (matriz estadual)",
    "esiapibaixas_impostos_encargos":  "API baixas",
    "esrpr11":  "Relatorios e obrigacoes (matriz estadual)",
    "esm87":  "Movimento e parametros (esm)",
    "esf03":  "Movimento fiscal (esf)",
    "esrrs02":  "Relatorios e obrigacoes (matriz estadual)",
    "esisitesefazrs06":  "Sefaz e sites estaduais",
    "esrrn04":  "Relatorios e obrigacoes (matriz estadual)",
    "esrpe03":  "Relatorios e obrigacoes (matriz estadual)",
    "esr42":  "Relatorios e obrigacoes (matriz estadual)",
    "esm57":  "Movimento e parametros (esm)",
    "esf11":  "Movimento fiscal (esf)",
    "esm46":  "Movimento e parametros (esm)",
    "esf22":  "Movimento fiscal (esf)",
    "esm75":  "Movimento e parametros (esm)",
    "esrpb02":  "Relatorios e obrigacoes (matriz estadual)",
    "esifixocfe01":  "SPED / layouts fixos e documentos eletronicos",
    "esrba08":  "Relatorios e obrigacoes (matriz estadual)",
    "esr17":  "Relatorios e obrigacoes (matriz estadual)",
    "esrpr14":  "Relatorios e obrigacoes (matriz estadual)",
    "esr_defis_api_contador":  "API contador / DEFIS / PGDAS / memorias",
    "esr35":  "Relatorios e obrigacoes (matriz estadual)",
    "esc20":  "Nucleo escrituracao (esc)",
    "esisiteportal":  "Cadastros site / portal / CTe",
    "esrrs15":  "Relatorios e obrigacoes (matriz estadual)",
    "esr_pgdas":  "API contador / DEFIS / PGDAS / memorias",
    "esifixonfse01":  "SPED / layouts fixos e documentos eletronicos",
    "esr60":  "Relatorios e obrigacoes (matriz estadual)",
    "esm07":  "Movimento e parametros (esm)",
    "esrmt04":  "Relatorios e obrigacoes (matriz estadual)",
    "esifixonfcom02":  "SPED / layouts fixos e documentos eletronicos",
    "esm84":  "Movimento e parametros (esm)",
    "esf16":  "Movimento fiscal (esf)",
    "esrpr09":  "Relatorios e obrigacoes (matriz estadual)",
    "esr46":  "Relatorios e obrigacoes (matriz estadual)",
    "esrse03":  "Relatorios e obrigacoes (matriz estadual)",
    "esm59":  "Movimento e parametros (esm)",
    "esrrj01":  "Relatorios e obrigacoes (matriz estadual)",
    "esm48":  "Movimento e parametros (esm)",
    "esrrs05":  "Relatorios e obrigacoes (matriz estadual)",
    "esrsc18":  "Relatorios e obrigacoes (matriz estadual)",
    "esrac02":  "Relatorios e obrigacoes (matriz estadual)",
    "esapuracaoempreendimento":  "Apuracao de impostos",
    "esrms03":  "Relatorios e obrigacoes (matriz estadual)",
    "esm74":  "Movimento e parametros (esm)",
    "esm65":  "Movimento e parametros (esm)",
    "esrce02":  "Relatorios e obrigacoes (matriz estadual)",
    "esr24":  "Relatorios e obrigacoes (matriz estadual)",
    "esrro06":  "Relatorios e obrigacoes (matriz estadual)",
    "esapuracaoconsulta02":  "Apuracao de impostos",
    "esr47":  "Relatorios e obrigacoes (matriz estadual)",
    "esr36":  "Relatorios e obrigacoes (matriz estadual)",
    "esr56":  "Relatorios e obrigacoes (matriz estadual)",
    "esr65":  "Relatorios e obrigacoes (matriz estadual)",
    "esrsc07":  "Relatorios e obrigacoes (matriz estadual)",
    "esifdipj1209":  "SPED / layouts DIPJ",
    "esricmsconvenio":  "Relatorios e obrigacoes (matriz estadual)",
    "esm09":  "Movimento e parametros (esm)",
    "esifixocfe02":  "SPED / layouts fixos e documentos eletronicos",
    "esifdipj1202":  "SPED / layouts DIPJ",
    "esiapibaixas":  "API baixas",
    "esrpr07":  "Relatorios e obrigacoes (matriz estadual)",
    "esrrs13":  "Relatorios e obrigacoes (matriz estadual)",
    "esxml":  "SPED / leiaute e XML",
    "esr07":  "Relatorios e obrigacoes (matriz estadual)",
    "esisitesefazes01":  "Sefaz e sites estaduais",
    "esplanejamentotributario":  "Planejamento tributario",
    "esrsc03":  "Relatorios e obrigacoes (matriz estadual)",
    "esrsp03":  "Relatorios e obrigacoes (matriz estadual)",
    "esf18":  "Movimento fiscal (esf)",
    "esm49":  "Movimento e parametros (esm)",
    "esrba03":  "Relatorios e obrigacoes (matriz estadual)",
    "esifixothreaddigitalbank":  "SPED / layouts fixos e documentos eletronicos",
    "esrsp13":  "Relatorios e obrigacoes (matriz estadual)",
    "esrmg03":  "Relatorios e obrigacoes (matriz estadual)",
    "esionbalance":  "Integracao Onvio / saldo",
    "esc24":  "Nucleo escrituracao (esc)",
    "esm17":  "Movimento e parametros (esm)",
    "esrpi02":  "Relatorios e obrigacoes (matriz estadual)",
    "esifdipj1301":  "SPED / layouts DIPJ",
    "esc21":  "Nucleo escrituracao (esc)",
    "esrma02":  "Relatorios e obrigacoes (matriz estadual)",
    "esr57":  "Relatorios e obrigacoes (matriz estadual)",
    "esr64":  "Relatorios e obrigacoes (matriz estadual)",
    "esifdipj1208":  "SPED / layouts DIPJ",
    "esifixoconvenio115icms02":  "SPED / layouts fixos e documentos eletronicos",
    "esc16":  "Nucleo escrituracao (esc)",
    "esres05":  "Relatorios e obrigacoes (matriz estadual)",
    "esrsp11":  "Relatorios e obrigacoes (matriz estadual)",
    "esm80":  "Movimento e parametros (esm)",
    "esrrj10":  "Relatorios e obrigacoes (matriz estadual)",
    "esr01":  "Relatorios e obrigacoes (matriz estadual)",
    "esifixocte02":  "SPED / layouts fixos e documentos eletronicos",
    "esapuracao14":  "Apuracao de impostos",
    "esifixonf302":  "SPED / layouts fixos e documentos eletronicos",
    "esr102":  "Relatorios e obrigacoes (matriz estadual)",
    "esrpa02":  "Relatorios e obrigacoes (matriz estadual)",
    "esm50":  "Movimento e parametros (esm)",
    "esrgo03":  "Relatorios e obrigacoes (matriz estadual)",
    "esr78":  "Relatorios e obrigacoes (matriz estadual)",
    "esrsc17":  "Relatorios e obrigacoes (matriz estadual)",
    "esrmg09":  "Relatorios e obrigacoes (matriz estadual)",
    "esm82":  "Movimento e parametros (esm)",
    "esc19":  "Nucleo escrituracao (esc)",
    "esrms05":  "Relatorios e obrigacoes (matriz estadual)",
    "esm11":  "Movimento e parametros (esm)",
    "esapuracao04":  "Apuracao de impostos",
    "esm33":  "Movimento e parametros (esm)",
    "esrrn01":  "Relatorios e obrigacoes (matriz estadual)",
    "esc27":  "Nucleo escrituracao (esc)",
    "esrpe05":  "Relatorios e obrigacoes (matriz estadual)",
    "esm47":  "Movimento e parametros (esm)",
    "esifixonfsenacional01":  "SPED / layouts fixos e documentos eletronicos",
    "esm34":  "Movimento e parametros (esm)",
    "esifdipj1309":  "SPED / layouts DIPJ",
    "esm25":  "Movimento e parametros (esm)",
    "esifdipj1407":  "SPED / layouts DIPJ",
    "esf06":  "Movimento fiscal (esf)",
    "esrms04":  "Relatorios e obrigacoes (matriz estadual)",
    "esifixoconvenio115icms01":  "SPED / layouts fixos e documentos eletronicos",
    "esapuracaosimplesnacional02":  "Apuracao de impostos",
    "esr98":  "Relatorios e obrigacoes (matriz estadual)",
    "esrmt05":  "Relatorios e obrigacoes (matriz estadual)",
    "esc07":  "Nucleo escrituracao (esc)",
    "esrpi03":  "Relatorios e obrigacoes (matriz estadual)",
    "esobj02":  "Nucleo escrituracao (esc)",
    "esrgo05":  "Relatorios e obrigacoes (matriz estadual)",
    "esrmg07":  "Relatorios e obrigacoes (matriz estadual)",
    "esrpa03":  "Relatorios e obrigacoes (matriz estadual)",
    "esm62":  "Movimento e parametros (esm)",
    "esral02":  "Relatorios e obrigacoes (matriz estadual)",
    "esutilalteracao08":  "Utilitarios e alteracoes",
    "esrpb01":  "Relatorios e obrigacoes (matriz estadual)",
    "esm32":  "Movimento e parametros (esm)",
    "esm23":  "Movimento e parametros (esm)",
    "esifdipj1401":  "SPED / layouts DIPJ",
    "esf08":  "Movimento fiscal (esf)",
    "esrpe01":  "Relatorios e obrigacoes (matriz estadual)",
    "esisitectedadoscarganfe":  "Cadastros site / portal / CTe",
    "esm51":  "Movimento e parametros (esm)",
    "esparcelamentoimpostosn":  "Parcelamento",
    "esifdipj1406":  "SPED / layouts DIPJ",
    "esr83":  "Relatorios e obrigacoes (matriz estadual)",
    "esrsp05":  "Relatorios e obrigacoes (matriz estadual)",
    "esr92":  "Relatorios e obrigacoes (matriz estadual)",
    "esrba09":  "Relatorios e obrigacoes (matriz estadual)",
    "esapuracao10":  "Apuracao de impostos",
    "esr11":  "Relatorios e obrigacoes (matriz estadual)",
    "esc01":  "Nucleo escrituracao (esc)",
    "esr22":  "Relatorios e obrigacoes (matriz estadual)",
    "esral03":  "Relatorios e obrigacoes (matriz estadual)",
    "esc04":  "Nucleo escrituracao (esc)",
    "esc15":  "Nucleo escrituracao (esc)",
    "esr50":  "Relatorios e obrigacoes (matriz estadual)",
    "esrsc11":  "Relatorios e obrigacoes (matriz estadual)",
    "esf20":  "Movimento fiscal (esf)",
    "esapuracaoestoque":  "Apuracao de impostos",
    "esisitecte01":  "Cadastros site / portal / CTe",
    "esrsc09":  "Relatorios e obrigacoes (matriz estadual)",
    "esifdipj1210":  "SPED / layouts DIPJ",
    "esm01":  "Movimento e parametros (esm)",
    "esrrj03":  "Relatorios e obrigacoes (matriz estadual)",
    "esidominioatendimento":  "Atendimento dominio (import NF-e)",
    "esm86":  "Movimento e parametros (esm)",
    "esisitesefazrs02":  "Sefaz e sites estaduais",
    "esf02":  "Movimento fiscal (esf)",
    "esionbalance03":  "Integracao Onvio / saldo",
    "esrpr02":  "Relatorios e obrigacoes (matriz estadual)",
    "esutilgraficos01":  "Utilitarios e alteracoes",
    "esrmg01":  "Relatorios e obrigacoes (matriz estadual)",
    "esrmt01":  "Relatorios e obrigacoes (matriz estadual)",
    "esrsp18":  "Relatorios e obrigacoes (matriz estadual)",
    "esm41":  "Movimento e parametros (esm)",
    "esf23":  "Movimento fiscal (esf)",
    "esm72":  "Movimento e parametros (esm)",
    "esm63":  "Movimento e parametros (esm)",
    "esm56":  "Movimento e parametros (esm)",
    "esrfLMC":  "Relatorios e obrigacoes (matriz estadual)",
    "esifixoempresarais":  "SPED / layouts fixos e documentos eletronicos",
    "esrto03":  "Relatorios e obrigacoes (matriz estadual)",
    "esr16":  "Relatorios e obrigacoes (matriz estadual)",
    "esr25":  "Relatorios e obrigacoes (matriz estadual)",
    "esr49":  "Relatorios e obrigacoes (matriz estadual)",
    "esr34":  "Relatorios e obrigacoes (matriz estadual)",
    "esrsc01":  "Relatorios e obrigacoes (matriz estadual)",
    "esf15":  "Movimento fiscal (esf)",
    "esisitesefazbase":  "Sefaz e sites estaduais",
    "esr84":  "Relatorios e obrigacoes (matriz estadual)",
    "esm36":  "Movimento e parametros (esm)",
    "esm_ajustes_inss_rb":  "Layouts / ajustes (prefixo esm_)",
    "esparcelamentoimposto":  "Parcelamento",
    "esrenomeado":  "Relatorios e obrigacoes (matriz estadual)",
    "esrrj05":  "Relatorios e obrigacoes (matriz estadual)",
    "esrrj02":  "Relatorios e obrigacoes (matriz estadual)",
    "esr09":  "Relatorios e obrigacoes (matriz estadual)",
    "esisitesefazrs03":  "Sefaz e sites estaduais",
    "esrpr08":  "Relatorios e obrigacoes (matriz estadual)",
    "esrpe06":  "Relatorios e obrigacoes (matriz estadual)",
    "esrse02":  "Relatorios e obrigacoes (matriz estadual)",
    "esrsp01":  "Relatorios e obrigacoes (matriz estadual)",
    "esm78":  "Movimento e parametros (esm)",
    "esrsp21":  "Relatorios e obrigacoes (matriz estadual)",
    "esm69":  "Movimento e parametros (esm)",
    "esrgo10":  "Relatorios e obrigacoes (matriz estadual)",
    "esrdf03":  "Relatorios e obrigacoes (matriz estadual)",
    "esr28":  "Relatorios e obrigacoes (matriz estadual)",
    "esc11":  "Nucleo escrituracao (esc)",
    "esm64":  "Movimento e parametros (esm)",
    "esrsc16":  "Relatorios e obrigacoes (matriz estadual)",
    "esm19":  "Movimento e parametros (esm)",
    "esrro07":  "Relatorios e obrigacoes (matriz estadual)",
    "esres01":  "Relatorios e obrigacoes (matriz estadual)",
    "esrgo04":  "Relatorios e obrigacoes (matriz estadual)",
    "esr48":  "Relatorios e obrigacoes (matriz estadual)",
    "esr59":  "Relatorios e obrigacoes (matriz estadual)",
    "esrgo09":  "Relatorios e obrigacoes (matriz estadual)",
    "esisitesefazmt01":  "Sefaz e sites estaduais",
    "escontabilizacao01":  "Contabilizacao",
    "esifdipj1206":  "SPED / layouts DIPJ",
    "esileiauteconjuntodados":  "SPED / leiaute e XML",
    "esifdipj1310":  "SPED / layouts DIPJ",
    "esiFixoBilhetePassagem01":  "SPED / layouts fixos e documentos eletronicos",
    "esr39":  "Relatorios e obrigacoes (matriz estadual)",
    "esrrn02":  "Relatorios e obrigacoes (matriz estadual)",
    "esrrj08":  "Relatorios e obrigacoes (matriz estadual)",
    "esrpr06":  "Relatorios e obrigacoes (matriz estadual)",
    "esrrs14":  "Relatorios e obrigacoes (matriz estadual)",
    "esrba04":  "Relatorios e obrigacoes (matriz estadual)",
    "esr06":  "Relatorios e obrigacoes (matriz estadual)",
    "esisitesefazes02":  "Sefaz e sites estaduais",
    "esmodulo":  "Nucleo escrituracao (esc)",
    "esrgdemonstrativosimpostos01":  "Relatorios e obrigacoes (matriz estadual)",
    "esrotinasautomaticasescrita":  "Rotinas automaticas - Escrita",
    "esrsp19":  "Relatorios e obrigacoes (matriz estadual)",
    "esm13":  "Movimento e parametros (esm)",
    "esrmg02":  "Relatorios e obrigacoes (matriz estadual)",
    "esiveiculosusados":  "Cadastros site / portal / CTe",
    "esexternos":  "Integracoes externas",
    "esc25":  "Nucleo escrituracao (esc)",
    "esm18":  "Movimento e parametros (esm)",
    "esr53":  "Relatorios e obrigacoes (matriz estadual)",
    "esifixoempresasefip":  "SPED / layouts fixos e documentos eletronicos",
    "esifdipj1307":  "SPED / layouts DIPJ",
    "esifdipj1203":  "SPED / layouts DIPJ",
    "esr51":  "Relatorios e obrigacoes (matriz estadual)",
    "esr81":  "Relatorios e obrigacoes (matriz estadual)",
    "esisitesefazms02":  "Sefaz e sites estaduais",
    "esrgo08":  "Relatorios e obrigacoes (matriz estadual)",
    "esr74":  "Relatorios e obrigacoes (matriz estadual)",
    "esifdipj1302":  "SPED / layouts DIPJ",
    "esifixoempresadipj":  "SPED / layouts fixos e documentos eletronicos",
    "esm90":  "Movimento e parametros (esm)",
    "esrsp12":  "Relatorios e obrigacoes (matriz estadual)",
    "esr99":  "Relatorios e obrigacoes (matriz estadual)",
    "esr_memoria_calculo_reducao":  "API contador / DEFIS / PGDAS / memorias",
    "esrrj09":  "Relatorios e obrigacoes (matriz estadual)",
    "esifixothreadasis":  "SPED / layouts fixos e documentos eletronicos",
    "esisitesefazgo01":  "Sefaz e sites estaduais",
    "esrsp20":  "Relatorios e obrigacoes (matriz estadual)",
    "esrgo07":  "Relatorios e obrigacoes (matriz estadual)",
    "esifixonfsesp02":  "SPED / layouts fixos e documentos eletronicos",
    "esrpa01":  "Relatorios e obrigacoes (matriz estadual)",
    "esrdf01":  "Relatorios e obrigacoes (matriz estadual)",
    "esrgo02":  "Relatorios e obrigacoes (matriz estadual)",
    "esselecao":  "Nucleo escrituracao (esc)",
    "esrmg08":  "Relatorios e obrigacoes (matriz estadual)",
    "esm60":  "Movimento e parametros (esm)",
    "esc18":  "Nucleo escrituracao (esc)",
    "esrsp08":  "Relatorios e obrigacoes (matriz estadual)",
    "esutilalteracao03":  "Utilitarios e alteracoes",
    "esm12":  "Movimento e parametros (esm)",
    "esrpr16":  "Relatorios e obrigacoes (matriz estadual)",
    "esm35":  "Movimento e parametros (esm)",
    "esrsp14":  "Relatorios e obrigacoes (matriz estadual)",
    "esrsp07":  "Relatorios e obrigacoes (matriz estadual)",
    "esm21":  "Movimento e parametros (esm)",
    "esr97":  "Relatorios e obrigacoes (matriz estadual)",
    "esrpr15":  "Relatorios e obrigacoes (matriz estadual)",
    "esr63":  "Relatorios e obrigacoes (matriz estadual)",
    "esifdipj1308":  "SPED / layouts DIPJ",
    "esm24":  "Movimento e parametros (esm)",
    "esifdipj1408":  "SPED / layouts DIPJ",
    "esrpr19":  "Relatorios e obrigacoes (matriz estadual)",
    "esisitesefazms01":  "Sefaz e sites estaduais",
    "esionbalance04":  "Integracao Onvio / saldo",
    "esrms07":  "Relatorios e obrigacoes (matriz estadual)",
    "esr_memoria_calculo_bilhete":  "API contador / DEFIS / PGDAS / memorias",
    "esf10":  "Movimento fiscal (esf)",
    "esc14":  "Nucleo escrituracao (esc)",
    "esc06":  "Nucleo escrituracao (esc)",
    "esifdacon01":  "Informativos / Dacon",
    "esrsc12":  "Relatorios e obrigacoes (matriz estadual)",
    "esr80":  "Relatorios e obrigacoes (matriz estadual)",
    "escpr01":  "Nucleo escrituracao (esc)",
    "esobj03":  "Nucleo escrituracao (esc)",
    "esisitesefazsc01":  "Sefaz e sites estaduais",
    "esrmg06":  "Relatorios e obrigacoes (matriz estadual)",
    "esrro01":  "Relatorios e obrigacoes (matriz estadual)",
    "esr15":  "Relatorios e obrigacoes (matriz estadual)",
    "esm03":  "Movimento e parametros (esm)",
    "esrrs20":  "Relatorios e obrigacoes (matriz estadual)",
    "esibuscaprodutos":  "Busca produtos",
    "esrba06":  "Relatorios e obrigacoes (matriz estadual)",
    "esm88":  "Movimento e parametros (esm)",
    "esifixoempresa":  "SPED / layouts fixos e documentos eletronicos",
    "esm30":  "Movimento e parametros (esm)",
    "esrrs19":  "Relatorios e obrigacoes (matriz estadual)",
    "esionbalance01":  "Integracao Onvio / saldo",
    "esm22":  "Movimento e parametros (esm)",
    "esifdipj1402":  "SPED / layouts DIPJ",
    "esrrn03":  "Relatorios e obrigacoes (matriz estadual)",
    "esrsp09":  "Relatorios e obrigacoes (matriz estadual)",
    "esm52":  "Movimento e parametros (esm)",
    "esf12":  "Movimento fiscal (esf)",
    "esm43":  "Movimento e parametros (esm)",
    "esf21":  "Movimento fiscal (esf)",
    "esrba05":  "Relatorios e obrigacoes (matriz estadual)",
    "esrotinasautomaticasimportacao":  "Rotinas automaticas - Importacao",
    "esr23":  "Relatorios e obrigacoes (matriz estadual)",
    "esr32":  "Relatorios e obrigacoes (matriz estadual)",
    "esrmt02":  "Relatorios e obrigacoes (matriz estadual)",
    "esifdipj1303":  "SPED / layouts DIPJ",
    "esf14":  "Movimento fiscal (esf)",
    "esr76":  "Relatorios e obrigacoes (matriz estadual)",
    "esrpr01":  "Relatorios e obrigacoes (matriz estadual)",
    "esm05":  "Movimento e parametros (esm)",
    "esrce01":  "Relatorios e obrigacoes (matriz estadual)",
    "esifixonfse02":  "SPED / layouts fixos e documentos eletronicos",
    "esm02":  "Movimento e parametros (esm)",
    "esrrs12":  "Relatorios e obrigacoes (matriz estadual)",
    "esifixonfcom01":  "SPED / layouts fixos e documentos eletronicos",
    "esreforma_simulador":  "Relatorios e obrigacoes (matriz estadual)",
    "esm89":  "Movimento e parametros (esm)",
    "esisitesefazrs05":  "Sefaz e sites estaduais",
    "esutilalteracao":  "Utilitarios e alteracoes",
    "esrpe04":  "Relatorios e obrigacoes (matriz estadual)",
    "esm20":  "Movimento e parametros (esm)",
    "esm54":  "Movimento e parametros (esm)",
    "esifdipj1410":  "SPED / layouts DIPJ",
    "esm45":  "Movimento e parametros (esm)",
    "esrce03":  "Relatorios e obrigacoes (matriz estadual)",
    "esm76":  "Movimento e parametros (esm)",
    "esf13":  "Movimento fiscal (esf)",
    "esrgo06":  "Relatorios e obrigacoes (matriz estadual)",
    "esm73":  "Movimento e parametros (esm)",
    "esr_defis":  "API contador / DEFIS / PGDAS / memorias",
    "esc10":  "Nucleo escrituracao (esc)",
    "esr38":  "Relatorios e obrigacoes (matriz estadual)",
    "esrto02":  "Relatorios e obrigacoes (matriz estadual)",
    "esrro05":  "Relatorios e obrigacoes (matriz estadual)",
    "esrpr10":  "Relatorios e obrigacoes (matriz estadual)",
    "esr33":  "Relatorios e obrigacoes (matriz estadual)",
    "esr29":  "Relatorios e obrigacoes (matriz estadual)",
    "esrgo01":  "Relatorios e obrigacoes (matriz estadual)",
    "esifixothreads":  "SPED / layouts fixos e documentos eletronicos",
    "esr_api_contador":  "API contador / DEFIS / PGDAS / memorias",
    "esrba10":  "Relatorios e obrigacoes (matriz estadual)",
    "esifdipj1204":  "SPED / layouts DIPJ",
    "esm04":  "Movimento e parametros (esm)",
    "esrap02":  "Relatorios e obrigacoes (matriz estadual)",
    "esrrj06":  "Relatorios e obrigacoes (matriz estadual)",
    "esifdipj1201":  "SPED / layouts DIPJ",
    "esrpr04":  "Relatorios e obrigacoes (matriz estadual)",
    "esrrs16":  "Relatorios e obrigacoes (matriz estadual)",
    "esconsultarpagamentoimpostoecac":  "Consulta e-CAC",
    "esr08":  "Relatorios e obrigacoes (matriz estadual)",
    "esutilalteracao09":  "Utilitarios e alteracoes",
    "esr73":  "Relatorios e obrigacoes (matriz estadual)",
    "esrac01":  "Relatorios e obrigacoes (matriz estadual)",
    "esrpr12":  "Relatorios e obrigacoes (matriz estadual)",
    "esr14":  "Relatorios e obrigacoes (matriz estadual)",
    "esm79":  "Movimento e parametros (esm)",
    "esm68":  "Movimento e parametros (esm)",
    "esapuracao12":  "Apuracao de impostos",
    "esifixonfce02":  "SPED / layouts fixos e documentos eletronicos",
    "esc23":  "Nucleo escrituracao (esc)",
    "esr44":  "Relatorios e obrigacoes (matriz estadual)",
    "esr_memoria_calculo_saida":  "API contador / DEFIS / PGDAS / memorias",
    "esr55":  "Relatorios e obrigacoes (matriz estadual)",
    "esrgo12":  "Relatorios e obrigacoes (matriz estadual)",
    "esr66":  "Relatorios e obrigacoes (matriz estadual)",
    "esrsc04":  "Relatorios e obrigacoes (matriz estadual)",
    "esm38":  "Movimento e parametros (esm)",
    "esr58":  "Relatorios e obrigacoes (matriz estadual)",
    "esifixosintegra02":  "SPED / layouts fixos e documentos eletronicos",
    "esisitesefazmt02":  "Sefaz e sites estaduais",
    "esifdipj1207":  "SPED / layouts DIPJ",
    "esr85":  "Relatorios e obrigacoes (matriz estadual)",
    "esr94":  "Relatorios e obrigacoes (matriz estadual)",
    "esrgo11":  "Relatorios e obrigacoes (matriz estadual)",
    "esr02":  "Relatorios e obrigacoes (matriz estadual)",
    "esm16":  "Movimento e parametros (esm)",
    "esr89":  "Relatorios e obrigacoes (matriz estadual)",
    "esifixoempresaspedecf":  "SPED / layouts fixos e documentos eletronicos",
    "esf17":  "Movimento fiscal (esf)",
    "esifixonf301":  "SPED / layouts fixos e documentos eletronicos",
    "esf24":  "Movimento fiscal (esf)",
    "esrgdemonstrativosimpostos02":  "Relatorios e obrigacoes (matriz estadual)",
    "esrsp16":  "Relatorios e obrigacoes (matriz estadual)",
    "esapuracao02":  "Apuracao de impostos",
    "esrdf04":  "Relatorios e obrigacoes (matriz estadual)",
    "esierninformativofiscal":  "Informativos / Dacon",
    "esm14":  "Movimento e parametros (esm)",
    "esifixonfce01":  "SPED / layouts fixos e documentos eletronicos",
    "esr68":  "Relatorios e obrigacoes (matriz estadual)",
    "esc22":  "Nucleo escrituracao (esc)",
    "esr96":  "Relatorios e obrigacoes (matriz estadual)",
    "esrotinasautomaticas":  "Rotinas automaticas",
    "esr43":  "Relatorios e obrigacoes (matriz estadual)",
    "esr52":  "Relatorios e obrigacoes (matriz estadual)",
    "esr61":  "Relatorios e obrigacoes (matriz estadual)",
    "esifdipj1306":  "SPED / layouts DIPJ",
    "esrpr18":  "Relatorios e obrigacoes (matriz estadual)",
    "esifixocompleto01":  "SPED / layouts fixos e documentos eletronicos",
    "esrrs10":  "Relatorios e obrigacoes (matriz estadual)",
    "esifixocte01":  "SPED / layouts fixos e documentos eletronicos",
    "esrsp15":  "Relatorios e obrigacoes (matriz estadual)",
    "esr95":  "Relatorios e obrigacoes (matriz estadual)",
    "esrrr01":  "Relatorios e obrigacoes (matriz estadual)",
    "esrmt06":  "Relatorios e obrigacoes (matriz estadual)",
    "esc08":  "Nucleo escrituracao (esc)",
    "esr30":  "Relatorios e obrigacoes (matriz estadual)",
    "esrrs03":  "Relatorios e obrigacoes (matriz estadual)",
    "esapuracao08":  "Apuracao de impostos",
    "esrmg04":  "Relatorios e obrigacoes (matriz estadual)",
    "esianalytics":  "Integracoes / painel e analytics",
    "esr71":  "Relatorios e obrigacoes (matriz estadual)",
    "esrpb03":  "Relatorios e obrigacoes (matriz estadual)",
    "esapuracao03":  "Apuracao de impostos",
    "esm70":  "Movimento e parametros (esm)",
    "esres04":  "Relatorios e obrigacoes (matriz estadual)",
    "esr62":  "Relatorios e obrigacoes (matriz estadual)",
    "esrpr17":  "Relatorios e obrigacoes (matriz estadual)",
    "esm31":  "Movimento e parametros (esm)",
    "esm81":  "Movimento e parametros (esm)",
    "esifixothreadupdate":  "SPED / layouts fixos e documentos eletronicos",
    "esifdipj1404":  "SPED / layouts DIPJ",
    "esf05":  "Movimento fiscal (esf)",
    "esrpr05":  "Relatorios e obrigacoes (matriz estadual)",
    "esr10":  "Relatorios e obrigacoes (matriz estadual)"
}
